{
  "nijmegen": {
    "color": {
      "green": {
        "25": {
          "value": "#0e6150"
        },
        "30": {
          "value": "#157c68"
        }
      },
      "blue": {
        "30": {
          "value": "#0092EF"
        },
        "40": {
          "value": "#40C4FF"
        }
      },
      "red": {
        "20": { "value": "#580518" },
        "30": { "value": "#a80a2d" },
        "22": { "value": "#890825" }
      },
      "white": {
        "10": {"value": "#FFFFFF"}
      },
      "grey": {
        "10": {
          "value": "#212121"
        },
        "15": {
          "value": "#2D2D2D"
        },
        "20": {
          "value": "#3a3a3a"
        },
        "35": {
          "value": "#767676"
        },
        "40": {
          "value": "#6C757D"
        },
        "50": {
          "value": "#000000"
        }
      }
    }
  }
}
